docku.build-0.1.0-py3.4-nspkg.pth
docku/build/__init__.py
docku.build-0.1.0.data/scripts/bootstrap_build
docku.build-0.1.0.dist-info/DESCRIPTION.rst
docku.build-0.1.0.dist-info/METADATA
docku.build-0.1.0.dist-info/metadata.json
docku.build-0.1.0.dist-info/namespace_packages.txt
docku.build-0.1.0.dist-info/RECORD
docku.build-0.1.0.dist-info/top_level.txt
docku.build-0.1.0.dist-info/WHEEL
