Metadata-Version: 2.0
Name: docku.build
Version: 0.1.0
Summary: Scaffolds out build meta files.
Home-page: https://github.com/docku/build
Author: Jon Chen
Author-email: bsd@voltaire.sh
License: MIT
Platform: UNKNOWN
Classifier: Intended Audience :: Developers
Classifier: License :: OSI Approved :: MIT License
Classifier: Operating System :: POSIX :: Linux
Classifier: Programming Language :: Python
Classifier: Programming Language :: Python :: 3
Classifier: Programming Language :: Python :: 3.2
Classifier: Programming Language :: Python :: 3.3
Classifier: Programming Language :: Python :: 3.4
Requires-Dist: cookiecutter (==1.0.0)
